cancer_data/.gitignore
cancer_data/__init__.py
cancer_data/access.py
cancer_data/checks.py
cancer_data/config.py
cancer_data/data/preview/.keep
cancer_data/data/processed/.keep
cancer_data/data/raw/.keep
cancer_data/data/reference/.keep
cancer_data/download.py
cancer_data/process.py
cancer_data/processors/ccle.py
cancer_data/processors/depmap.py
cancer_data/processors/gtex.py
cancer_data/processors/other.py
cancer_data/processors/tcga.py
cancer_data/schema.csv
cancer_data/utils.py
cancer_data-0.3.6.dist-info/LICENSE.txt
cancer_data-0.3.6.dist-info/METADATA
cancer_data-0.3.6.dist-info/WHEEL
cancer_data-0.3.6.dist-info/RECORD
