Metadata-Version: 2.1
Name: cancer_data
Version: 0.3.6
Summary: Preprocessing for various cancer genomics datasets
Home-page: https://github.com/kevinhu/cancer_data
License: MIT
Keywords: cancer,data,genomics
Author: Kevin Hu
Author-email: kevinhuwest@gmail.com
Requires-Python: >=3.9,<4.0
Classifier: License :: OSI Approved :: MIT License
Classifier: Programming Language :: Python :: 3
Classifier: Programming Language :: Python :: 3.9
Classifier: Programming Language :: Python :: 3.10
Classifier: Programming Language :: Python :: 3.11
Classifier: Programming Language :: Python :: 3.12
Requires-Dist: gtfparse (>=2.5.0,<3.0.0)
Requires-Dist: pandas (>=2.2.1,<3.0.0)
Requires-Dist: requests (>=2.31.0,<3.0.0)
Requires-Dist: scipy (>=1.13.0,<2.0.0)
Requires-Dist: tables (>=3.9.2,<4.0.0)
Requires-Dist: tqdm (>=4.66.2,<5.0.0)
Requires-Dist: xlrd (>=2.0.1)
Project-URL: Repository, https://github.com/kevinhu/cancer_data
